pwbus_request/__init__.py
pwbus_request/pwbus_bottle_request.py
pwbus_request/request.py
pwbus_request-0.1.9.dist-info/LICENSE.txt
pwbus_request-0.1.9.dist-info/METADATA
pwbus_request-0.1.9.dist-info/WHEEL
pwbus_request-0.1.9.dist-info/top_level.txt
pwbus_request-0.1.9.dist-info/RECORD
