Metadata-Version: 2.1
Name: pwbus-request
Version: 0.1.9
Summary: API to make request for PWBUS. Developed for the following frameworks Flask, Bottle
Home-page: https://github.com/fszostak/pwbus-request
Author: Fabio Szostak
Author-email: fszostak@gmail.com
License: UNKNOWN
Platform: UNKNOWN
Classifier: Development Status :: 4 - Beta
Classifier: Programming Language :: Python :: 3.7
Classifier: Programming Language :: Python :: 3.8
Classifier: License :: OSI Approved :: MIT License
Classifier: Operating System :: OS Independent
Requires-Python: >=3.7
Requires-Dist: requests (==2.25.1)
